toyrl/__init__.py
toyrl/a2c.py
toyrl/dqn.py
toyrl/ppo.py
toyrl/py.typed
toyrl/reinforce.py
toyrl/sarsa.py
toyrl-0.3.1.dist-info/licenses/LICENSE
toyrl-0.3.1.dist-info/METADATA
toyrl-0.3.1.dist-info/WHEEL
toyrl-0.3.1.dist-info/top_level.txt
toyrl-0.3.1.dist-info/zip-safe
toyrl-0.3.1.dist-info/RECORD
