Metadata-Version: 2.4
Name: toyrl
Version: 0.3.1
Summary: A clean reinforcement learning library
Author-email: Xiangzhuang Shen <datahonor@gmail.com>
License-Expression: Apache-2.0
Project-URL: Homepage, https://ai-glimpse.github.io/toyrl
Project-URL: Bug Tracker, https://github.com/ai-glimpse/toyrl/issues
Project-URL: Documentation, https://ai-glimpse.github.io/toyrl
Project-URL: Source Code, https://github.com/ai-glimpse/toyrl
Project-URL: Release Notes, https://github.com/ai-glimpse/toyrl/releases
Classifier: Development Status :: 3 - Alpha
Classifier: Intended Audience :: Science/Research
Classifier: Intended Audience :: Developers
Classifier: Operating System :: OS Independent
Classifier: Programming Language :: Python :: 3.12
Classifier: Programming Language :: Python :: 3.13
Requires-Python: >=3.12
License-File: LICENSE
Requires-Dist: gymnasium[classic-control]>=1.1.1
Requires-Dist: numpy>=2.2.5
Requires-Dist: torch>=2.7.0
Requires-Dist: wandb>=0.19.10
Provides-Extra: dev
Requires-Dist: pre-commit; extra == "dev"
Requires-Dist: ipython; extra == "dev"
Requires-Dist: mypy; extra == "dev"
Requires-Dist: ruff; extra == "dev"
Requires-Dist: pytest; extra == "dev"
Requires-Dist: pytest-cov; extra == "dev"
Requires-Dist: pytest-sugar; extra == "dev"
Requires-Dist: hypothesis>=6.112.0; extra == "dev"
Provides-Extra: docs
Requires-Dist: mkdocs; extra == "docs"
Requires-Dist: mkdocs-material; extra == "docs"
Requires-Dist: mkdocs-material-extensions; extra == "docs"
Requires-Dist: mkdocstrings; extra == "docs"
Requires-Dist: mkdocs-bibtex; extra == "docs"
Requires-Dist: mkdocstrings-python; extra == "docs"
Requires-Dist: mkdocs-autorefs; extra == "docs"
Requires-Dist: mkdocs-git-committers-plugin-2; extra == "docs"
Requires-Dist: mkdocs-git-revision-date-localized-plugin; extra == "docs"
Dynamic: license-file
